keycove/__init__.py
keycove/generate.py
keycove/security.py
keycove/utils.py
keycove-0.3.5.dist-info/LICENSE
keycove-0.3.5.dist-info/METADATA
keycove-0.3.5.dist-info/WHEEL
keycove-0.3.5.dist-info/top_level.txt
keycove-0.3.5.dist-info/RECORD
