Metadata-Version: 2.1
Name: keycove
Version: 0.3.5
Summary: An API authentication library. Create, verify, and securely store API keys.
Home-page: https://github.com/keycove/keycove
Author: Jaz Allibhai
Author-email: jaz.allibhai@gmail.com
License: MIT
License-File: LICENSE
